{"url":"http:\/\/cloud.local\/rest\/event.get.json","info":{"url":"http:\/\/cloud.local\/rest\/event.get.json","content_type":"application\/json; charset=utf-8","http_code":200,"header_size":830,"request_size":251,"filetime":-1,"ssl_verify_result":0,"redirect_count":0,"total_time":1.486969,"namelookup_time":0.001011,"connect_time":0.001122,"pretransfer_time":0.00114,"size_upload":75,"size_download":435,"speed_download":292,"speed_upload":50,"download_content_length":-1,"upload_content_length":75,"starttransfer_time":1.486936,"redirect_time":0,"redirect_url":"","primary_ip":"172.18.0.6","certinfo":[],"primary_port":80,"local_ip":"172.18.0.8","local_port":37700,"http_version":2,"protocol":1,"ssl_verifyresult":0,"scheme":"HTTP","appconnect_time_us":0,"connect_time_us":1122,"namelookup_time_us":1011,"pretransfer_time_us":1140,"redirect_time_us":0,"starttransfer_time_us":1486936,"total_time_us":1486969},"params":{"method":"event.get","params":{"auth":"73cd5a68000000140000001100000001706207aa65f4009d4757c6a76c6a72f36b4d57"},"this_auth":"N"},"result":{"result":[{"event":"ONCRMDYNAMICITEMADD","connector_id":"test-app-connector","offline":1},{"event":"ONSUBSCRIPTIONRENEW","handler":"http:\/\/app.local\/index.php?page=event_handler","auth_type":"1","offline":0}],"time":{"start":1750777699.426166,"finish":1750777700.530684,"duration":1.104517936706543,"processing":0.002424955368041992,"date_start":"2025-06-24T15:08:19+00:00","date_finish":"2025-06-24T15:08:20+00:00","operating":0}}}