{"url":"http:\/\/cloud.local\/rest\/event.get.json","info":{"url":"http:\/\/cloud.local\/rest\/event.get.json","content_type":"application\/json; charset=utf-8","http_code":200,"header_size":830,"request_size":251,"filetime":-1,"ssl_verify_result":0,"redirect_count":0,"total_time":0.853333,"namelookup_time":0.000508,"connect_time":0.000586,"pretransfer_time":0.000611,"size_upload":75,"size_download":662,"speed_download":775,"speed_upload":87,"download_content_length":-1,"upload_content_length":75,"starttransfer_time":0.853293,"redirect_time":0,"redirect_url":"","primary_ip":"172.18.0.10","certinfo":[],"primary_port":80,"local_ip":"172.18.0.3","local_port":36522,"http_version":2,"protocol":1,"ssl_verifyresult":0,"scheme":"HTTP","appconnect_time_us":0,"connect_time_us":586,"namelookup_time_us":508,"pretransfer_time_us":611,"redirect_time_us":0,"starttransfer_time_us":853293,"total_time_us":853333},"params":{"method":"event.get","params":{"auth":"4a2a656800000014000000110000000170620774eb25c8c8f2719bd950bdab47a071d5"},"this_auth":"N"},"result":{"result":[{"event":"ONCRMDYNAMICITEMADD","connector_id":"test-app-connector","offline":1},{"event":"ONAPPPAYMENT","handler":"http:\/\/app.local\/index.php?page=event_handler","auth_type":"1","offline":0},{"event":"ONAPPUPDATE","handler":"http:\/\/app.local\/index.php?page=event_handler","auth_type":"1","offline":0},{"event":"ONSUBSCRIPTIONRENEW","handler":"http:\/\/app.local\/index.php?page=event_handler","auth_type":"1","offline":0}],"time":{"start":1751456827.042606,"finish":1751456827.690654,"duration":0.648047924041748,"processing":0.008122920989990234,"date_start":"2025-07-02T11:47:07+00:00","date_finish":"2025-07-02T11:47:07+00:00","operating":0}}}